memoized_lambda/__init__.py
memoized_lambda/py.typed
memoized_lambda-0.1.dist-info/LICENSE
memoized_lambda-0.1.dist-info/METADATA
memoized_lambda-0.1.dist-info/WHEEL
memoized_lambda-0.1.dist-info/top_level.txt
memoized_lambda-0.1.dist-info/RECORD
